azure/keyvault/certificates/__init__.py
azure/keyvault/certificates/_client.py
azure/keyvault/certificates/_enums.py
azure/keyvault/certificates/_models.py
azure/keyvault/certificates/_polling.py
azure/keyvault/certificates/_sdk_moniker.py
azure/keyvault/certificates/_version.py
azure/keyvault/certificates/py.typed
azure/keyvault/certificates/_generated/__init__.py
azure/keyvault/certificates/_generated/_client.py
azure/keyvault/certificates/_generated/_configuration.py
azure/keyvault/certificates/_generated/_patch.py
azure/keyvault/certificates/_generated/_serialization.py
azure/keyvault/certificates/_generated/_vendor.py
azure/keyvault/certificates/_generated/py.typed
azure/keyvault/certificates/_generated/_operations/__init__.py
azure/keyvault/certificates/_generated/_operations/_operations.py
azure/keyvault/certificates/_generated/_operations/_patch.py
azure/keyvault/certificates/_generated/aio/__init__.py
azure/keyvault/certificates/_generated/aio/_client.py
azure/keyvault/certificates/_generated/aio/_configuration.py
azure/keyvault/certificates/_generated/aio/_patch.py
azure/keyvault/certificates/_generated/aio/_vendor.py
azure/keyvault/certificates/_generated/aio/_operations/__init__.py
azure/keyvault/certificates/_generated/aio/_operations/_operations.py
azure/keyvault/certificates/_generated/aio/_operations/_patch.py
azure/keyvault/certificates/_generated/models/__init__.py
azure/keyvault/certificates/_generated/models/_enums.py
azure/keyvault/certificates/_generated/models/_models.py
azure/keyvault/certificates/_generated/models/_patch.py
azure/keyvault/certificates/_shared/__init__.py
azure/keyvault/certificates/_shared/_polling.py
azure/keyvault/certificates/_shared/_polling_async.py
azure/keyvault/certificates/_shared/async_challenge_auth_policy.py
azure/keyvault/certificates/_shared/async_client_base.py
azure/keyvault/certificates/_shared/challenge_auth_policy.py
azure/keyvault/certificates/_shared/client_base.py
azure_keyvault_certificates-4.8.0.dist-info/LICENSE
azure_keyvault_certificates-4.8.0.dist-info/METADATA
azure_keyvault_certificates-4.8.0.dist-info/WHEEL
azure_keyvault_certificates-4.8.0.dist-info/top_level.txt
azure_keyvault_certificates-4.8.0.dist-info/RECORD
